preceptron/__init__.py
preceptron/perceptron.py
perceptron_pypi-0.0.1.dist-info/LICENSE
perceptron_pypi-0.0.1.dist-info/METADATA
perceptron_pypi-0.0.1.dist-info/WHEEL
perceptron_pypi-0.0.1.dist-info/top_level.txt
perceptron_pypi-0.0.1.dist-info/RECORD
