Metadata-Version: 2.1
Name: perceptron-pypi
Version: 0.0.1
Summary: its an implimentation of Perceptron
Home-page: https://github.com/Akash-Modi104/perceptron_pypi
Author: Akash Modi
Author-email: developer.akash104@gmail.com
License: UNKNOWN
Project-URL: Bug Tracker, https://github.com/Akash-Modi104/perceptron_pypi/issues
Platform: UNKNOWN
Classifier: Programming Language :: Python :: 3
Classifier: License :: OSI Approved :: MIT License
Classifier: Operating System :: OS Independent
Requires-Python: >=3.7
License-File: LICENSE
Requires-Dist: numpy
Requires-Dist: tqdm
